moveread/dfy_connector/__init__.py
moveread/dfy_connector/pull.py
moveeread_dfy_connector-0.1.0.dist-info/METADATA
moveeread_dfy_connector-0.1.0.dist-info/WHEEL
moveeread_dfy_connector-0.1.0.dist-info/top_level.txt
moveeread_dfy_connector-0.1.0.dist-info/RECORD
