Metadata-Version: 2.1
Name: moveeread-dfy-connector
Version: 0.1.0
Summary: Daemons to connect Moveread DFY and the pipeline
Author-email: Marcel Claramunt <marcel@moveread.com>
Project-URL: repo, https://github.com/moveread/dfy-pipeline.git
Requires-Python: >=3.10
Requires-Dist: moveread-dfy
Requires-Dist: moveread-pipelines-dfy
Requires-Dist: haskellian
Requires-Dist: pure-cv
Requires-Dist: kv-api
Requires-Dist: sqlmodel
Requires-Dist: dslog
